bsv_language_server/__init__.py
bsv_language_server/bsv_parser.py
bsv_language_server/server.py
bsv_language_server-0.1.0.dist-info/licenses/LICENSE
bsv_language_server-0.1.0.dist-info/METADATA
bsv_language_server-0.1.0.dist-info/WHEEL
bsv_language_server-0.1.0.dist-info/entry_points.txt
bsv_language_server-0.1.0.dist-info/top_level.txt
bsv_language_server-0.1.0.dist-info/RECORD
