Metadata-Version: 2.4
Name: bsv-language-server
Version: 0.1.0
Summary: A Language Server for Bluespec SystemVerilog
Requires-Python: >=3.10
License-File: LICENSE
Requires-Dist: pygls>=2.0.0
Requires-Dist: tree-sitter>=0.25.2
Requires-Dist: tree-sitter-bsv>=0.1.0
Dynamic: license-file
